cvstudio/__init__.py
cvstudio/__main__.py
cvstudio/assets/icons/cvstudio/annotations.png
cvstudio/assets/icons/cvstudio/check_all.png
cvstudio/assets/icons/cvstudio/circle.png
cvstudio/assets/icons/cvstudio/clean.png
cvstudio/assets/icons/cvstudio/cube.png
cvstudio/assets/icons/cvstudio/cursor.png
cvstudio/assets/icons/cvstudio/data.png
cvstudio/assets/icons/cvstudio/database.png
cvstudio/assets/icons/cvstudio/delete.png
cvstudio/assets/icons/cvstudio/download.png
cvstudio/assets/icons/cvstudio/edit.png
cvstudio/assets/icons/cvstudio/first.png
cvstudio/assets/icons/cvstudio/folder_empty.png
cvstudio/assets/icons/cvstudio/github.png
cvstudio/assets/icons/cvstudio/highlighter.png
cvstudio/assets/icons/cvstudio/image.png
cvstudio/assets/icons/cvstudio/last.png
cvstudio/assets/icons/cvstudio/left.png
cvstudio/assets/icons/cvstudio/loading.gif
cvstudio/assets/icons/cvstudio/logout.png
cvstudio/assets/icons/cvstudio/new_folder.png
cvstudio/assets/icons/cvstudio/placeholder.png
cvstudio/assets/icons/cvstudio/polygon.png
cvstudio/assets/icons/cvstudio/refresh.png
cvstudio/assets/icons/cvstudio/right.png
cvstudio/assets/icons/cvstudio/robotic-hand.png
cvstudio/assets/icons/cvstudio/save-icon.png
cvstudio/assets/icons/cvstudio/square.png
cvstudio/assets/icons/cvstudio/uncheck_all.png
cvstudio/assets/icons/cvstudio/upload.png
cvstudio/assets/icons/dark/annotations.png
cvstudio/assets/icons/dark/check_all.png
cvstudio/assets/icons/dark/circle.png
cvstudio/assets/icons/dark/clean.png
cvstudio/assets/icons/dark/config.png
cvstudio/assets/icons/dark/cube.png
cvstudio/assets/icons/dark/cursor.png
cvstudio/assets/icons/dark/data.png
cvstudio/assets/icons/dark/database.png
cvstudio/assets/icons/dark/delete.png
cvstudio/assets/icons/dark/delete_label.png
cvstudio/assets/icons/dark/download.png
cvstudio/assets/icons/dark/edit.png
cvstudio/assets/icons/dark/experiments.png
cvstudio/assets/icons/dark/first.png
cvstudio/assets/icons/dark/folder.png
cvstudio-0.1.0.dist-info/entry_points.txt
cvstudio-0.1.0.dist-info/WHEEL
cvstudio-0.1.0.dist-info/METADATA
cvstudio-0.1.0.dist-info/RECORD
