Metadata-Version: 2.1
Name: cvstudio
Version: 0.1.0
Summary: Computer vision projects annotation tools
Author: haruiz
Author-email: henryruiz22@gmail.com
Requires-Python: >=3.7,<4.0
Classifier: Programming Language :: Python :: 3
Classifier: Programming Language :: Python :: 3.7
Classifier: Programming Language :: Python :: 3.8
Classifier: Programming Language :: Python :: 3.9
Requires-Dist: dask[complete] (>=2.30.0,<3.0.0)
Requires-Dist: hurry (>=1.1,<2.0)
Requires-Dist: hurry.filesize (>=0.9,<0.10)
Requires-Dist: imutils (>=0.5.3,<0.6.0)
Requires-Dist: mako (>=1.1.3,<2.0.0)
Requires-Dist: marshmallow (>=3.8.0,<4.0.0)
Requires-Dist: matplotlib (>=3.3.2,<4.0.0)
Requires-Dist: more_itertools (>=8.5.0,<9.0.0)
Requires-Dist: numpy (>=1.19.2,<2.0.0)
Requires-Dist: opencv-python (==4.1.0.25)
Requires-Dist: pandas (>=1.1.3,<2.0.0)
Requires-Dist: peewee (>=3.13.3,<4.0.0)
Requires-Dist: pyqt5 (>=5.15.1,<6.0.0)
